MANIFEST.in
README.md
requirements.txt
setup.cfg
setup.py
versioneer.py
botcity/plugins/ftp/__init__.py
botcity/plugins/ftp/_version.py
botcity/plugins/ftp/plugin.py
botcity_ftp_plugin.egg-info/PKG-INFO
botcity_ftp_plugin.egg-info/SOURCES.txt
botcity_ftp_plugin.egg-info/dependency_links.txt
botcity_ftp_plugin.egg-info/requires.txt
botcity_ftp_plugin.egg-info/top_level.txt