Metadata-Version: 2.1
Name: botcity-ftp-plugin
Version: 0.1.3
Home-page: https://bitbucket.org/botcitydev/bot-ftp-plugin-python.git
Requires-Python: >=3.7
